TSFEDL/__init__.py
TSFEDL/blocks_keras.py
TSFEDL/blocks_pytorch.py
TSFEDL/data.py
TSFEDL/models_keras.py
TSFEDL/models_pytorch.py
TSFEDL/utils.py
TSFEDL-1.0.7.7.dist-info/LICENSE
TSFEDL-1.0.7.7.dist-info/METADATA
TSFEDL-1.0.7.7.dist-info/WHEEL
TSFEDL-1.0.7.7.dist-info/top_level.txt
TSFEDL-1.0.7.7.dist-info/RECORD
