Metadata-Version: 2.1
Name: TSFEDL
Version: 1.0.7.7
Summary: Time Series Spatio-Temporal Feature Extraction using Deep Learning
Home-page: https://github.com/ari-dasci/S-TSFE-DL
Author: Ignacio Aguilera Martos, Ángel Miguel García Vico, Julian Luengo, Francisco Herrera
Author-email: nacheteam@ugr.es
Keywords: Time series,Feature extraction,Deep learning,recurrent,cnn
Requires-Python: >=3.8
License-File: LICENSE
Requires-Dist: scikit-learn
Requires-Dist: wfdb
Requires-Dist: obspy
Requires-Dist: tensorflow
Requires-Dist: keras
Requires-Dist: pytorch-lightning
Requires-Dist: torchmetrics
